downs/__init__.py
downs/_down.py
downs/_thread.py
downs-1.0.5.dist-info/LICENSE
downs-1.0.5.dist-info/METADATA
downs-1.0.5.dist-info/WHEEL
downs-1.0.5.dist-info/top_level.txt
downs-1.0.5.dist-info/RECORD
