Metadata-Version: 2.1
Name: downs
Version: 1.0.5
Summary: Multithreaded Download Tool.
Home-page: https://github.com/userElaina
Author: userElaina
Author-email: userElaina@google.com
License: UNKNOWN
Project-URL: Source, https://github.com/userelaina/downs
Keywords: download thread
Platform: UNKNOWN
Classifier: License :: OSI Approved :: MIT License
Classifier: Programming Language :: Python :: 3
Classifier: Programming Language :: Python :: 3.6
Classifier: Programming Language :: Python :: 3.7
Classifier: Programming Language :: Python :: 3.8
Classifier: Programming Language :: Python :: 3.9
Requires-Python: >=3.6
